{"name":"Create new list","id":"yourlogo;create-new-list","testSteps":[{"number":1,"description":"Create new list #1: {email\u003dcmanco@choucairtesting.com, password\u003dabc123, name\u003dNuevalista}","duration":15279,"startTime":"2022-04-13T16:08:54.207-05:00[America/Bogota]","screenshots":[{"screenshot":"04caf51369dfec6342431fcf58ee934486081f573e12fd909d01d142f8de3bb1.png"}],"result":"SUCCESS","precondition":false,"children":[{"number":2,"description":"Given than Crihstian wants to visit the yourlogo page","duration":5434,"startTime":"2022-04-13T16:08:54.271-05:00[America/Bogota]","screenshots":[{"screenshot":"ab86a1a2c6eda7a8c56a23a51a49a50fc5a2f3d6f0812e4ec0afdfbf2cf5e324.png"}],"result":"SUCCESS","precondition":false,"children":[{"number":3,"description":"Crihstian opens the Your logo page","duration":4670,"startTime":"2022-04-13T16:08:54.640-05:00[America/Bogota]","screenshots":[{"screenshot":"ab86a1a2c6eda7a8c56a23a51a49a50fc5a2f3d6f0812e4ec0afdfbf2cf5e324.png"}],"result":"SUCCESS","precondition":false}]},{"number":4,"description":"And he login to the yourlogo page\r\n| email | password |\r\n| cmanco@choucairtesting.com | abc123 |","duration":5225,"startTime":"2022-04-13T16:08:59.705-05:00[America/Bogota]","screenshots":[{"screenshot":"270b4a6b65c5fabb8e83aa1022cefb2fd2e4cecc40d35b12feb52f4949818b26.png"}],"result":"SUCCESS","precondition":false,"children":[{"number":5,"description":"Crihstian clicks on Boton login","duration":1608,"startTime":"2022-04-13T16:08:59.743-05:00[America/Bogota]","screenshots":[{"screenshot":"efb467e8bc4fb61562205d2f702e9e0b8bfee0a67d7c755398e771fc0bc5f444.png"}],"result":"SUCCESS","precondition":false},{"number":6,"description":"Crihstian enters \u0027cmanco@choucairtesting.com\u0027 into Caja de texto correo","duration":491,"startTime":"2022-04-13T16:09:01.353-05:00[America/Bogota]","screenshots":[{"screenshot":"edb516a358cc054f99d71f064f0a39a28cce264aa806b795a1ebed3a09a1fc92.png"}],"result":"SUCCESS","precondition":false},{"number":7,"description":"Crihstian enters \u0027abc123\u0027 into Caja de texto contrasena","duration":455,"startTime":"2022-04-13T16:09:01.846-05:00[America/Bogota]","screenshots":[{"screenshot":"eb6dbb2db37d2eed4f2969d2466f452935c2ad2e6e758604b67560a5269175fa.png"}],"result":"SUCCESS","precondition":false},{"number":8,"description":"Crihstian clicks on Boton entrar","duration":2436,"startTime":"2022-04-13T16:09:02.304-05:00[America/Bogota]","screenshots":[{"screenshot":"270b4a6b65c5fabb8e83aa1022cefb2fd2e4cecc40d35b12feb52f4949818b26.png"}],"result":"SUCCESS","precondition":false}]},{"number":9,"description":"When Being in the MY WISH LISTS section enter a new name for the wish list\r\n| name |\r\n| Nuevalista |","duration":3598,"startTime":"2022-04-13T16:09:04.931-05:00[America/Bogota]","screenshots":[{"screenshot":"04caf51369dfec6342431fcf58ee934486081f573e12fd909d01d142f8de3bb1.png"}],"result":"SUCCESS","precondition":false,"children":[{"number":10,"description":"Crihstian clicks on Boton My Wishlists","duration":1425,"startTime":"2022-04-13T16:09:04.969-05:00[America/Bogota]","screenshots":[{"screenshot":"04caf51369dfec6342431fcf58ee934486081f573e12fd909d01d142f8de3bb1.png"}],"result":"SUCCESS","precondition":false},{"number":11,"description":"Crihstian enters \u0027Nuevalista\u0027 into Caja de texto nombre","duration":519,"startTime":"2022-04-13T16:09:06.397-05:00[America/Bogota]","screenshots":[{"screenshot":"97f63a640b86ca9218f00f42d46a55d6ed6e8778ad2a21551b2bf872d6d29cf1.png"}],"result":"SUCCESS","precondition":false},{"number":12,"description":"Crihstian clicks on Boton Save","duration":1420,"startTime":"2022-04-13T16:09:06.920-05:00[America/Bogota]","screenshots":[{"screenshot":"04caf51369dfec6342431fcf58ee934486081f573e12fd909d01d142f8de3bb1.png"}],"result":"SUCCESS","precondition":false}]},{"number":13,"description":"Then he validates that the new wishlist has been created","duration":773,"startTime":"2022-04-13T16:09:08.530-05:00[America/Bogota]","screenshots":[{"screenshot":"04caf51369dfec6342431fcf58ee934486081f573e12fd909d01d142f8de3bb1.png"}],"result":"SUCCESS","precondition":false,"children":[{"number":14,"description":"Then result2","duration":388,"startTime":"2022-04-13T16:09:08.738-05:00[America/Bogota]","screenshots":[{"screenshot":"04caf51369dfec6342431fcf58ee934486081f573e12fd909d01d142f8de3bb1.png"}],"result":"SUCCESS","precondition":false}]}]}],"userStory":{"id":"yourlogo","storyName":"yourlogo","path":"src/test/resources/features/ejemplo001_.feature","narrative":"  As a user, I want to add new items to the wish list","type":"feature"},"featureTag":{"name":"Features/yourlogo","type":"feature"},"title":"Create new list","tags":[{"name":"HU3","type":"tag"},{"name":"prueba2","type":"tag"},{"name":"Yourlogo","type":"feature"}],"startTime":"2022-04-13T16:08:53.585-05:00[America/Bogota]","duration":18217,"projectKey":"","sessionId":"1848d33b047f6f98e8e1d32dd2b1e464","driver":"chrome:crihstian","dataTable":{"headers":["email","password","name"],"rows":[{"values":["cmanco@choucairtesting.com","abc123","Nuevalista"],"result":"SUCCESS"}],"predefinedRows":true,"scenarioOutline":"Given than Crihstian wants to visit the yourlogo page\n\rAnd he login to the yourlogo page\n\rWhen Being in the MY WISH LISTS section enter a new name for the wish list\n\rThen he validates that the new wishlist has been created\n\r","dataSetDescriptors":[{"startRow":0,"rowCount":0,"name":""}]},"manual":false,"testSource":"Cucumber","result":"SUCCESS"}